formations_api/__init__.py
formations_api/connection.py
formations_api/models.py
formations_api/utils.py
formations_api/crud/__init__.py
formations_api/crud/create.py
formations_api/crud/delete.py
formations_api/crud/read.py
formations_api/crud/update.py
formations_api-0.2.0.dist-info/METADATA
formations_api-0.2.0.dist-info/WHEEL
formations_api-0.2.0.dist-info/RECORD
