Metadata-Version: 2.4
Name: formations_api
Version: 0.2.0
Summary: Software Development Kit for Formations API
Project-URL: Homepage, https://github.com/tdg-formations-app/formations-sdk
Project-URL: Issues, https://github.com/tdg-formations-app/formations-sdk/issues
Author-email: Sebástian Narváez <sebnarvaez19@gmail.com>
Classifier: Programming Language :: Python :: 3
Requires-Python: >=3.10
Requires-Dist: pandas==2.2.2
Requires-Dist: pydantic>=2.8.2
Requires-Dist: requests>=2.32.3
